blessmore/__init__.py
blessmore/clean_data.py
blessmore/shonaembeddings.py
blessmore/train_embedding.py
blessmore-3.0.3.dist-info/METADATA
blessmore-3.0.3.dist-info/WHEEL
blessmore-3.0.3.dist-info/top_level.txt
blessmore-3.0.3.dist-info/RECORD
