Metadata-Version: 2.1
Name: blessmore
Version: 3.0.3
Summary: A python package to load Shona FastText embeddings,Train Fasttext Embedding and clean Shona text data
Home-page: https://github.com/Blessmore2/blessmore
Author: Blessmore Majongwe
Author-email: blessmoremajongwe@gmail.com
License: Apache 2.0
Classifier: Programming Language :: Python :: 3
Classifier: License :: OSI Approved :: Apache Software License
Classifier: Operating System :: OS Independent
Requires-Python: >=2.7
Requires-Dist: gensim
Requires-Dist: huggingface-hub
Requires-Dist: regex
